strategytester5/__init__.py
strategytester5/_html_templates.py
strategytester5/_swap.py
strategytester5/error_description.py
strategytester5/stats.py
strategytester5/tester.py
strategytester5/hist/__init__.py
strategytester5/hist/bars.py
strategytester5/hist/manager.py
strategytester5/hist/tick_gen.py
strategytester5/hist/ticks.py
strategytester5/mt5/__init__.py
strategytester5/mt5/constants.py
strategytester5/mt5/exporter.py
strategytester5/mt5/importer.py
strategytester5/trade_classes/AccountInfo.py
strategytester5/trade_classes/DealInfo.py
strategytester5/trade_classes/HistoryOrderInfo.py
strategytester5/trade_classes/OrderInfo.py
strategytester5/trade_classes/PositionInfo.py
strategytester5/trade_classes/SymbolInfo.py
strategytester5/trade_classes/Trade.py
strategytester5/trade_classes/__init__.py
strategytester5/validators/__init__.py
strategytester5/validators/tester_configs.py
strategytester5/validators/trade.py
strategytester5-1.5.5.dist-info/licenses/LICENSE
strategytester5-1.5.5.dist-info/METADATA
strategytester5-1.5.5.dist-info/WHEEL
strategytester5-1.5.5.dist-info/top_level.txt
strategytester5-1.5.5.dist-info/RECORD
