Metadata-Version: 2.4
Name: strategytester5
Version: 1.5.5
Summary: A Python-based MetaTrader strategy tester for the MetaTrader5 module
Author-email: Omega Joctan Msigwa <omegajoctan@gmail.com>
License: MIT License
Project-URL: Homepage, https://github.com/MegaJoctan/StrategyTester5
Project-URL: Repository, https://github.com/MegaJoctan/StrategyTester5
Keywords: MetaTrader5,MetaTrader4,Strategytester,strategytesting,MT5,trading,forex,backtesting,algorithmic trading
Classifier: Intended Audience :: Developers
Classifier: Intended Audience :: Financial and Insurance Industry
Classifier: License :: OSI Approved :: MIT License
Classifier: Operating System :: Microsoft :: Windows
Classifier: Operating System :: POSIX :: Linux
Classifier: Operating System :: MacOS
Classifier: Programming Language :: Python :: 3
Classifier: Programming Language :: Python :: 3 :: Only
Classifier: Programming Language :: Python :: 3.9
Classifier: Programming Language :: Python :: 3.10
Classifier: Programming Language :: Python :: 3.11
Classifier: Programming Language :: Python :: 3.12
Classifier: Topic :: Software Development :: Libraries
Classifier: Topic :: Office/Business :: Financial
Classifier: Topic :: Scientific/Engineering
Requires-Python: >=3.9
License-File: LICENSE
Requires-Dist: numpy
Requires-Dist: polars
Requires-Dist: matplotlib
Requires-Dist: seaborn
Requires-Dist: tqdm
Requires-Dist: numba
Requires-Dist: scipy
Provides-Extra: mt5
Requires-Dist: metatrader5; extra == "mt5"
Dynamic: license-file
